paid_client/__init__.py
paid_client/core.py
paid_client-0.2.0.dist-info/LICENSE
paid_client-0.2.0.dist-info/METADATA
paid_client-0.2.0.dist-info/WHEEL
paid_client-0.2.0.dist-info/top_level.txt
paid_client-0.2.0.dist-info/RECORD
